README.md
setup.py
mgclipboard/__init__.py
mgclipboard.egg-info/PKG-INFO
mgclipboard.egg-info/SOURCES.txt
mgclipboard.egg-info/dependency_links.txt
mgclipboard.egg-info/top_level.txt
mgclipboard/middleware/__init__.py
mgclipboard/middleware/apps.py
mgclipboard/middleware/clipboard.py
mgclipboard/middleware/tests.py