Metadata-Version: 2.1
Name: mgclipboard
Version: 0.3.0
Summary: Clipboard middleware for Papermerge DMS
Home-page: https://github.com/papermerge/mg-clipboard
Author: Eugen Ciur
Author-email: eugen@papermerge.com
License: Apache 2.0 License
Keywords: Middleware,Django,Papermerge,DMS
Platform: UNKNOWN
Classifier: Programming Language :: Python :: 3
Classifier: License :: OSI Approved :: Apache Software License
Classifier: Operating System :: OS Independent
Requires-Python: >=3.6
